sampkg/__init__.py
sampkg/sammod/__init__.py
sampkg/sammod/sammod.py
sampkg-0.1.1.dist-info/LICENSE
sampkg-0.1.1.dist-info/METADATA
sampkg-0.1.1.dist-info/WHEEL
sampkg-0.1.1.dist-info/top_level.txt
sampkg-0.1.1.dist-info/RECORD
