Metadata-Version: 2.1
Name: sampkg
Version: 0.1.1
Summary: A sample Python package
Home-page: https://github.com/pgtgrly/
Author: Pranav Garg
Author-email: pranavgarg@gmail.com
License: UNKNOWN
Download-URL: https://github.com/pgtgrly//archive/0.1.1.tar.gz
Keywords: python,example
Platform: UNKNOWN
Requires-Dist: numpy
